obp_python/__init__.py
obp_python/api_client.py
obp_python/configuration.py
obp_python/rest.py
obp_python/api/__init__.py
obp_python/api/account_access_api.py
obp_python/api/account_api.py
obp_python/api/account_application_api.py
obp_python/api/account_firehose_api.py
obp_python/api/account_information_service__ais_api.py
obp_python/api/account_metadata_api.py
obp_python/api/account_public_api.py
obp_python/api/aggregate_metrics_api.py
obp_python/api/api_api.py
obp_python/api/api_collection_api.py
obp_python/api/atm_api.py
obp_python/api/authentication_type_validation_api.py
obp_python/api/bank_api.py
obp_python/api/branch_api.py
obp_python/api/card_api.py
obp_python/api/confirmation_of_funds_service__piis_api.py
obp_python/api/connector_method_api.py
obp_python/api/consent_api.py
obp_python/api/consumer_api.py
obp_python/api/counterparty_api.py
obp_python/api/counterparty_metadata_api.py
obp_python/api/customer_api.py
obp_python/api/customer_meeting_api.py
obp_python/api/customer_message_api.py
obp_python/api/d_auth_api.py
obp_python/api/data_warehouse_api.py
obp_python/api/direct_debit_api.py
obp_python/api/documentation_api.py
obp_python/api/dynamic_endpoint_manage_api.py
obp_python/api/dynamic_entity_manage_api.py
obp_python/api/dynamic_message_doc_api.py
obp_python/api/dynamic_resource_doc_api.py
obp_python/api/endpoint_mapping_api.py
obp_python/api/entitlement_api.py
obp_python/api/experimental_api.py
obp_python/api/firehose_data_api.py
obp_python/api/fx_api.py
obp_python/api/json_schema_validation_api.py
obp_python/api/kyc_api.py
obp_python/api/method_routing_api.py
obp_python/api/metric_api.py
obp_python/api/new_style_api.py
obp_python/api/onboarding_api.py
obp_python/api/owner_view_required_api.py
obp_python/api/payment_initiation_service__pis_api.py
obp_python/api/person_api.py
obp_python/api/private_data_api.py
obp_python/api/product_api.py
obp_python/api/product_collection_api.py
obp_python/api/psd2_api.py
obp_python/api/public_data_api.py
obp_python_apiv5-0.0.2.dist-info/METADATA
obp_python_apiv5-0.0.2.dist-info/WHEEL
obp_python_apiv5-0.0.2.dist-info/top_level.txt
obp_python_apiv5-0.0.2.dist-info/RECORD
